setup.py
colordesk/__init__.py
colordesk/cli.py
colordesk/core.py
colordesk/errors.py
colordesk/server.py
colordesk.egg-info/PKG-INFO
colordesk.egg-info/SOURCES.txt
colordesk.egg-info/dependency_links.txt
colordesk.egg-info/entry_points.txt
colordesk.egg-info/requires.txt
colordesk.egg-info/top_level.txt