Metadata-Version: 1.0
Name: colordesk
Version: 0.1.0
Summary: A format & renderer for color palette
Home-page: https://github.com/reorx/colordesk
Author: reorx
Author-email: novoreorx@gmail.com
License: UNKNOWN
Platform: UNKNOWN
